{
  "faint": "pk(generations_core:sandshrew, faintstart)",
  "poses": {
    "standing": {
      "animations": [
        "pk(generations_core:sandshrew.pk, idle)"
      ],
      "poseName": "standing",
      "poseTypes": [
        "PORTRAIT",
        "NONE",
        "PROFILE",
        "STAND",
        "FLOAT"
      ]
    },
    "walking": {
      "animations": [
        "pk(generations_core:sandshrew.pk, walk)"
      ],
      "poseName": "walking",
      "poseTypes": [
        "WALK"
      ]
    },
    "sleeping": {
      "animations": [
        "pk(generations_core:sandshrew.pk, sleeploop)"
      ],
      "poseName": "sleeping",
      "poseTypes": [
        "SLEEP"
      ]
    }
  }
}