{
  "implemented": true,
  "name": "Shroodle",
  "nationalPokedexNumber": 944,
  "primaryType": "poison",
  "secondaryType": "normal",
  "abilities": [
    "unburden",
    "pickpocket",
    "h:prankster"
  ],
  "drops": {
    "amount": 1,
    "entries": [
      {
        "item": "cobblemon:nanab_berry",
        "percentage": 2.5
      }
    ]
  },
  "baseStats": {
    "hp": 40,
    "attack": 65,
    "defence": 35,
    "special_attack": 40,
    "special_defence": 35,
    "speed": 75
  },
  "catchRate": 190,
  "maleRatio": 0.5,
  "baseExperienceYield": 58,
  "baseFriendship": 50,
  "evYield": {
    "hp": 0,
    "attack": 0,
    "defence": 0,
    "special_attack": 0,
    "special_defence": 0,
    "speed": 1
  },
  "experienceGroup": "medium_slow",
  "eggCycles": 20,
  "eggGroups": [
    "field"
  ],
  "behaviour": {
    "resting": {
      "canSleep": true,
      "willSleepOnBed": true,
      "depth": "normal",
      "light": "0-4"
    }
  },
  "moves": [
    "1:leer",
    "1:scratch",
    "5:acidspray",
    "8:bite",
    "8:furyswipes",
    "11:switcheroo",
    "14:poisonfang",
    "18:flatter",
    "21:slash",
    "25:uturn",
    "29:poisonjab",
    "33:taunt",
    "36:substitute",
    "40:knockoff",
    "45:gunkshot",
    "egg:copycat",
    "egg:crosspoison",
    "egg:partingshot",
    "egg:superfang",
    "egg:swagger",
    "egg:toxic",
    "tm:acidspray",
    "tm:acrobatics",
    "tm:batonpass",
    "tm:dig",
    "tm:encore",
    "tm:endure",
    "tm:facade",
    "tm:fling",
    "tm:foulplay",
    "tm:gunkshot",
    "tm:helpinghand",
    "tm:metronome",
    "tm:mudshot",
    "tm:mudslap",
    "tm:nastyplot",
    "tm:poisonjab",
    "tm:pounce",
    "tm:protect",
    "tm:raindance",
    "tm:rest",
    "tm:sleeptalk",
    "tm:sludgebomb",
    "tm:substitute",
    "tm:sunnyday",
    "tm:swordsdance",
    "tm:takedown",
    "tm:taunt",
    "tm:terablast",
    "tm:thief",
    "tm:trailblaze",
    "tm:uturn",
    "tm:venoshock"
  ],
  "labels": [
    "gen9"
  ],
  "aspects": [],
  "height": 2,
  "weight": 7,
  "evolutions": [
    {
      "id": "shroodle_grafaiai",
      "variant": "level_up",
      "result": "grafaiai",
      "consumeHeldItem": false,
      "learnableMoves": [
        "doodle"
      ],
      "requirements": [
        {
          "variant": "level",
          "minLevel": 28
        }
      ]
    }
  ],
  "baseScale": 0.6,
  "hitbox": {
    "width": 0.5,
    "height": 0.5,
    "fixed": false
  },
  "cannotDynamax": false,
  "pokedex": [
    "cobblemon.species.shroodle.desc"
  ]
}