{
  "implemented": true,
  "name": "Stoutland",
  "nationalPokedexNumber": 508,
  "primaryType": "normal",
  "abilities": [
    "intimidate",
    "sandrush",
    "h:scrappy"
  ],
  "drops": {
    "amount": 7,
    "entries": [
      {
        "item": "minecraft:bone",
        "quantityRange": "0-3"
      },
      {
        "item": "minecraft:blue_wool",
        "quantityRange": "2-3"
      },
      {
        "item": "cobblemon:chilan_berry",
        "percentage": 10.0
      }
    ]
  },
  "baseStats": {
    "hp": 85,
    "attack": 110,
    "defence": 90,
    "special_attack": 45,
    "special_defence": 90,
    "speed": 80
  },
  "catchRate": 45,
  "maleRatio": 0.5,
  "shoulderMountable": false,
  "baseExperienceYield": 250,
  "experienceGroup": "medium_slow",
  "eggCycles": 15,
  "eggGroups": [
    "field"
  ],
  "moves": [
    "1:bite",
    "1:firefang",
    "1:icefang",
    "1:leer",
    "1:odorsleuth",
    "1:tackle",
    "1:thunderfang",
    "1:workup",
    "12:retaliate",
    "19:babydolleyes",
    "24:playrough",
    "30:crunch",
    "38:takedown",
    "46:helpinghand",
    "54:reversal",
    "62:roar",
    "70:lastresort",
    "78:gigaimpact",
    "tm:aerialace",
    "tm:attract",
    "tm:charm",
    "tm:confide",
    "tm:crunch",
    "tm:dig",
    "tm:doubleteam",
    "tm:endure",
    "tm:facade",
    "tm:firefang",
    "tm:frustration",
    "tm:gigaimpact",
    "tm:helpinghand",
    "tm:hiddenpower",
    "tm:hyperbeam",
    "tm:hypervoice",
    "tm:icefang",
    "tm:ironhead",
    "tm:payback",
    "tm:playrough",
    "tm:protect",
    "tm:psychicfangs",
    "tm:raindance",
    "tm:rest",
    "tm:retaliate",
    "tm:return",
    "tm:reversal",
    "tm:roar",
    "tm:rocksmash",
    "tm:rocktomb",
    "tm:round",
    "tm:secretpower",
    "tm:shadowball",
    "tm:sleeptalk",
    "tm:snarl",
    "tm:snore",
    "tm:stompingtantrum",
    "tm:strength",
    "tm:substitute",
    "tm:sunnyday",
    "tm:superpower",
    "tm:surf",
    "tm:swagger",
    "tm:thunder",
    "tm:thunderbolt",
    "tm:thunderfang",
    "tm:thunderwave",
    "tm:toxic",
    "tm:uproar",
    "tm:wildcharge",
    "tm:workup",
    "tutor:afteryou",
    "tutor:covet",
    "tutor:helpinghand",
    "tutor:hypervoice",
    "tutor:ironhead",
    "tutor:lastresort",
    "tutor:shockwave",
    "tutor:sleeptalk",
    "tutor:snore",
    "tutor:stompingtantrum",
    "tutor:superpower",
    "tutor:uproar"
  ],
  "labels": [
    "gen5"
  ],
  "pokedex": [
    "cobblemon.species.stoutland.desc"
  ],
  "preEvolution": "herdier",
  "evolutions": [],
  "baseScale": 1,
  "hitbox": {
    "width": 1.4,
    "height": 1.8,
    "fixed": false
  },
  "baseFriendship": 50,
  "evYield": {
    "hp": 0,
    "attack": 3,
    "defence": 0,
    "special_attack": 0,
    "special_defence": 0,
    "speed": 0
  },
  "height": 12,
  "weight": 610,
  "aspects": [],
  "cannotDynamax": false
}