{
    "enabled": true,
    "neededInstalledMods": [],
    "neededUninstalledMods": [],
    "spawns": [
        {
            "id": "corsola-1",
            "pokemon": "corsola",
            "presets": [
                "water"
            ],
            "type": "pokemon",
            "context": "submerged",
            "bucket": "common",
            "level": "4-33",
            "weight": 10.0,
            "condition": {
                "canSeeSky": true,
                "biomes": [
                    "#cobblemon:is_warm_ocean"
                ],
                "timeRange": "day"
            }
        },
        {
            "id": "corsola-galarian-1",
            "pokemon": "corsola galarian",
            "presets": [
                "water"
            ],
            "type": "pokemon",
            "context": "seafloor",
            "bucket": "common",
            "level": "4-33",
            "weight": 10.0,
            "condition": {
                "canSeeSky": true,
                "biomes": [
                    "#cobblemon:is_warm_ocean"
                ],
                "timeRange": "night"
            }
        }
    ]
}