{
    "enabled": true,
    "neededInstalledMods": [],
    "neededUninstalledMods": [],
    "spawns": [
        {
            "id": "ninjask-1",
            "pokemon": "ninjask",
            "presets": [
                "natural"
            ],
            "type": "pokemon",
            "context": "grounded",
            "bucket": "uncommon",
            "level": "20-55",
            "weight": 5.0,
            "condition": {
                "canSeeSky": true,
                "timeRange": "night",
                "biomes": [
                    "#cobblemon:is_forest"
                ]
            }
        }
    ]
}