{
    "enabled": "false",
    "neededInstalledMods": [],
    "neededUninstalledMods": [],
    "spawns": [
        {
            "id": "phione-1",
            "pokemon": "phione",
            "presets": [
                "natural"
            ],
            "type": "pokemon",
            "context": "surface",
            "bucket": "ultra-rare",
            "level": "70-75",
            "weight": 0.001,
            "condition": {
                "biomes": [
                    "#cobblemon:is_ocean"
                ]
            }
        }
    ]
}