{
    "enabled": "true",
    "neededInstalledMods": [],
    "neededUninstalledMods": [],
    "spawns": [
        {
            "id": "sawk-1",
            "pokemon": "sawk",
            "presets": [
                "natural"
            ],
            "type": "pokemon",
            "context": "grounded",
            "bucket": "rare",
            "level": "25-60",
            "weight": 1.8,
            "condition": {
                "canSeeSky": true,
                "biomes": [
                    "#cobblemon:is_mountain"
                ]
            }
        }
    ]
}