{
    "enabled": true,
    "neededInstalledMods": [],
    "neededUninstalledMods": [],
    "spawns": [
        {
            "id": "comfey-1",
            "pokemon": "comfey",
            "presets": [
                "natural"
            ],
            "type": "pokemon",
            "context": "grounded",
            "bucket": "common",
            "level": "12-50",
            "weight": 9.0,
            "condition": {
                "canSeeSky": true,
                "biomes": [
                    "#cobblemon:is_floral",
                    "#cobblemon:is_magical"
                ]
            }
        }
    ]
}