{
  "type": "minecraft:crafting_shapeless",
  "category": "misc",
  "ingredients": [
    {
      "item": "generations_core:litleo_tuft"
    },
    {
      "item": "generations_core:litleo_tuft"
    },
    {
      "item": "generations_core:litleo_tuft"
    },
    {
      "item": "generations_core:houndour_fang"
    },
    {
      "item": "generations_core:houndour_fang"
    },
    {
      "item": "generations_core:houndour_fang"
    },
    {
      "item": "generations_core:numel_lava"
    },
    {
      "item": "generations_core:numel_lava"
    },
    {
      "item": "generations_core:numel_lava"
    }
  ],
  "result": {
    "item": "generations_core:tm_125"
  }
}