{
    "target": "cobblemon:hitmonchan",
    "drops": {
        "amount": 2,
        "entries": [
            {
                "item": "cobblemon:black_belt",
                "percentage": 5.0
            },
            {
                "item": "cobblemon:payapa_berry",
                "percentage": 5.0
            },
            {
                "item": "generations_core:scroll_page",
                "percentage": 1.0
            }
        ]
    },
    "behaviour": {
        "resting": {
            "canSleep": true,
            "willSleepOnBed": false,
            "depth": "normal",
            "light": "0-4"
        }
    }
}