{
  "type": "minecraft:chest",
  "pools": [
    {
      "bonus_rolls": 0.0,
      "entries": [
        {
          "type": "minecraft:item",
          "name": "cobblemon:antidote"
        },
        {
          "type": "minecraft:item",
          "name": "cobblemon:berry_juice"
        },
        {
          "type": "minecraft:item",
          "name": "cobblemon:blunder_policy"
        },
        {
          "type": "minecraft:item",
          "name": "cobblemon:cell_battery"
        },
        {
          "type": "minecraft:item",
          "name": "cobblemon:choice_scarf"
        },
        {
          "type": "minecraft:item",
          "name": "cobblemon:custap_berry"
        },
        {
          "type": "minecraft:item",
          "name": "cobblemon:float_stone"
        },
        {
          "type": "minecraft:item",
          "name": "cobblemon:haban_berry"
        },
        {
          "type": "minecraft:item",
          "name": "cobblemon:hard_stone"
        },
        {
          "type": "minecraft:item",
          "name": "cobblemon:health_feather"
        },
        {
          "type": "minecraft:item",
          "name": "cobblemon:kasib_berry"
        },
        {
          "type": "minecraft:item",
          "name": "cobblemon:max_potion"
        },
        {
          "type": "minecraft:item",
          "name": "cobblemon:metal_powder"
        },
        {
          "type": "minecraft:item",
          "name": "cobblemon:nanab_berry"
        },
        {
          "type": "minecraft:item",
          "name": "cobblemon:pomeg_berry"
        },
        {
          "type": "minecraft:item",
          "name": "cobblemon:power_anklet"
        },
        {
          "type": "minecraft:item",
          "name": "cobblemon:power_band"
        },
        {
          "type": "minecraft:item",
          "name": "cobblemon:protector"
        },
        {
          "type": "minecraft:item",
          "name": "cobblemon:quick_claw"
        },
        {
          "type": "minecraft:item",
          "name": "cobblemon:salac_berry"
        },
        {
          "type": "minecraft:item",
          "name": "cobblemon:spelon_berry"
        },
        {
          "type": "minecraft:item",
          "name": "cobblemon:zinc"
        },
        {
          "type": "minecraft:item",
          "name": "minecraft:feather"
        },
        {
          "type": "minecraft:item",
          "name": "minecraft:porkchop"
        },
        {
          "type": "minecraft:item",
          "name": "minecraft:rabbit_foot"
        },
        {
          "type": "minecraft:item",
          "name": "minecraft:music_disc_stal"
        },
        {
          "type": "minecraft:item",
          "name": "cobblemon:sassy_mint"
        },
        {
          "type": "minecraft:item",
          "name": "cobblemon:careful_mint"
        }
      ],
      "rolls": {
        "type": "minecraft:uniform",
        "max": 2.0,
        "min": 1.0
      }
    }
  ],
  "random_sequence": "generations_core:chests/quick_ball"
}