{
  "implemented": true,
  "name": "Shedinja",
  "nationalPokedexNumber": 292,
  "primaryType": "bug",
  "secondaryType": "ghost",
  "abilities": [
    "wonderguard"
  ],
  "baseStats": {
    "hp": 1,
    "attack": 90,
    "defence": 45,
    "special_attack": 30,
    "special_defence": 30,
    "speed": 40
  },
  "catchRate": 45,
  "maleRatio": -1,
  "shoulderMountable": false,
  "baseExperienceYield": 83,
  "experienceGroup": "erratic",
  "eggCycles": 15,
  "eggGroups": [
    "mineral"
  ],
  "behaviour": {
    "moving": {
      "fly": {
        "canFly": true
      }
    },
    "resting": {
      "canSleep": true,
      "willSleepOnBed": false,
      "depth": "normal",
      "light": "0-4"
    }
  },
  "moves": [
    "1:dig",
    "1:falseswipe",
    "1:grudge",
    "1:harden",
    "1:metalclaw",
    "1:mudslap",
    "1:sandattack",
    "1:scratch",
    "1:shadowclaw",
    "5:leechlife",
    "15:confuseray",
    "23:absorb",
    "29:shadowsneak",
    "36:furyswipes",
    "41:healblock",
    "43:mindreader",
    "50:shadowball",
    "57:spite",
    "64:phantomforce",
    "form_change:agility",
    "form_change:batonpass",
    "form_change:screech",
    "form_change:slash",
    "form_change:swordsdance",
    "tm:aerialace",
    "tm:agility",
    "tm:allyswitch",
    "tm:bugbuzz",
    "tm:confide",
    "tm:cut",
    "tm:dig",
    "tm:doubleteam",
    "tm:dreameater",
    "tm:endure",
    "tm:facade",
    "tm:falseswipe",
    "tm:flash",
    "tm:frustration",
    "tm:gigadrain",
    "tm:gigaimpact",
    "tm:hex",
    "tm:hiddenpower",
    "tm:honeclaws",
    "tm:hyperbeam",
    "tm:leechlife",
    "tm:naturalgift",
    "tm:phantomforce",
    "tm:protect",
    "tm:rest",
    "tm:return",
    "tm:round",
    "tm:sandstorm",
    "tm:secretpower",
    "tm:shadowball",
    "tm:shadowclaw",
    "tm:sleeptalk",
    "tm:snore",
    "tm:solarbeam",
    "tm:strugglebug",
    "tm:substitute",
    "tm:sunnyday",
    "tm:swagger",
    "tm:telekinesis",
    "tm:thief",
    "tm:toxic",
    "tm:trick",
    "tm:willowisp",
    "tm:xscissor",
    "tutor:allyswitch",
    "tutor:bugbite",
    "tutor:confuseray",
    "tutor:doubleedge",
    "tutor:dreameater",
    "tutor:endure",
    "tutor:furycutter",
    "tutor:gigadrain",
    "tutor:grudge",
    "tutor:mimic",
    "tutor:mudslap",
    "tutor:nightmare",
    "tutor:poltergeist",
    "tutor:shadowball",
    "tutor:skittersmack",
    "tutor:sleeptalk",
    "tutor:snore",
    "tutor:spite",
    "tutor:stringshot",
    "tutor:substitute",
    "tutor:suckerpunch",
    "tutor:swagger",
    "tutor:telekinesis",
    "tutor:trick"
  ],
  "labels": [
    "gen3"
  ],
  "pokedex": [
    "cobblemon.species.shedinja.desc"
  ],
  "preEvolution": "nincada",
  "evolutions": [],
  "baseScale": 0.7,
  "hitbox": {
    "width": 0.7,
    "height": 1.3,
    "fixed": false
  },
  "baseFriendship": 50,
  "evYield": {
    "hp": 2,
    "attack": 0,
    "defence": 0,
    "special_attack": 0,
    "special_defence": 0,
    "speed": 0
  },
  "height": 8,
  "weight": 12,
  "aspects": [],
  "cannotDynamax": false
}